{
    "gyms":{
        "enabled":"False",
        "ignore_neutral":"False",
        "filters":[
            {
                "from_team":["Valor", "Instinct", "Mystic"], "to_team":["Valor", "Instinct", "Mystic"],
                "min_dist":"0", "max_dist":"inf"
            }
        ]
    },
    "pokestops":{
        "enabled":"False",
        "filters":{ "min_dist":"0", "max_dist":"10" }
    },
  	"pokemon": {
		"enabled": "True",
		"default": {
			"min_cp": "0",
			"max_cp": "4760",
			"min_iv": "100",
			"max_iv": "100",
			"min_atk": "15",
			"max_atk": "15",
			"min_def": "15",
			"max_def": "15",
			"min_sta": "15",
			"max_sta": "15",
			"ignore_missing": "True"
		},
        "bulbasaur":"True",
"ivysaur":"True",
"venusaur":"True",
"charmander":"True",
"charmeleon":"True",
"charizard":"True",
"squirtle":"True",
"wartortle":"True",
"blastoise":"True",
"butterfree":"True",
"beedrill":"True",
"pidgeot":"True",
"raticate":"True",
"fearow":"True",
"ekans":"True",
"arbok":"True",
"pikachu":"True",
"raichu":"True",
"sandshrew":"True",
"sandslash":"True",
"nidoqueen":"True",
"nidoking":"True",
"clefable":"True",
"vulpix":"True",
"ninetales":"True",
"wigglytuff":"True",
"oddish":"True",
"gloom":"True",
"vileplume":"True",
"parasect":"True",
"diglett":"True",
"dugtrio":"True",
"meowth":"True",
"persian":"True",
"psyduck":"True",
"golduck":"True",
"mankey":"True",
"primeape":"True",
"growlithe":"True",
"arcanine":"True",
"poliwag":"True",
"poliwhirl":"True",
"poliwrath":"True",
"abra":"True",
"kadabra":"True",
"alakazam":"True",
"machop":"True",
"machoke":"True",
"machamp":"True",
"bellsprout":"True",
"victreebel":"True",
"tentacool":"True",
"geodude":"True",
"graveler":"True",
"golem":"True",
"ponyta":"True",
"rapidash":"True",
"slowpoke":"True",
"slowbro":"True",
"magnemite":"True",
"magneton":"True",
"farfetch'd":"True",
"doduo":"True",
"dodrio":"True",
"seel":"True",
"dewgong":"True",
"grimer":"True",
"muk":"True",
"shellder":"True",
"cloyster":"True",
"gastly":"True",
"haunter":"True",
"gengar":"True",
"onix":"True",
"voltorb":"True",
"electrode":"True",
"exeggcute":"True",
"exeggutor":"True",
"cubone":"True",
"marowak":"True",
"hitmonlee":"True",
"hitmonchan":"True",
"lickitung":"True",
"rhyhorn":"True",
"rhydon":"True",
"chansey":"True",
"tangela":"True",
"kangaskhan":"True",
"horsea":"True",
"seadra":"True",
"mr. mime":"True",
"staryu":"True",
"scyther":"True",
"jynx":"True",
"electabuzz":"True",
"magmar":"True",
"pinsir":"True",
"tauros":"True",
"magikarp":"True",
"gyarados":"True",
"lapras":"True",
"ditto":"True",
"eevee":"True",
"vaporeon":"True",
"jolteon":"True",
"flareon":"True",
"porygon":"True",
"omanyte":"True",
"omastar":"True",
"kabuto":"True",
"kabutops":"True",
"aerodactyl":"True",
"snorlax":"True",
"articuno":"True",
"zapdos":"True",
"moltres":"True",
"dratini":"True",
"dragonair":"True",
"dragonite":"True",
"mewtwo":"True",
"mew":"True",
"chikorita":"True",
"bayleef":"True",
"meganium":"True",
"cyndaquil":"True",
"quilava":"True",
"typhlosion":"True",
"totodile":"True",
"croconaw":"True",
"feraligatr":"True",
"chinchou":"True",
"lanturn":"True",
"togetic":"True",
"mareep":"True",
"flaaffy":"True",
"ampharos":"True",
"sudowoodo":"True",
"jumpluff":"True",
"aipom":"True",
"sunkern":"True",
"yanma":"True",
"espeon":"True",
"umbreon":"True",
"murkrow":"True",
"misdreavus":"True",
"unown":"True",
"wobbuffet":"True",
"girafarig":"True",
"pineco":"True",
"gligar":"True",
"steelix":"True",
"granbull":"True",
"shuckle":"True",
"heracross":"True",
"sneasel":"True",
"teddiursa":"True",
"ursaring":"True",
"slugma":"True",
"swinub":"True",
"piloswine":"True",
"corsola":"True",
"delibird":"True",
"mantine":"True",
"skarmory":"True",
"houndour":"True",
"houndoom":"True",
"phanpy":"True",
"donphan":"True",
"stantler":"True",
"smeargle":"True",
"tyrogue":"True",
"hitmontop":"True",
"miltank":"True",
"blissey":"True",
"raikou":"True",
"entei":"True",
"suicune":"True",
"larvitar":"True",
"pupitar":"True",
"tyranitar":"True",
"lugia":"True",
"ho-oh":"True",
"celebi":"True",
"treecko":"True",
"grovyle":"True",
"sceptile":"True",
"torchic":"True",
"combusken":"True",
"blaziken":"True",
"mudkip":"True",
"marshtomp":"True",
"swampert":"True",
"poochyena":"True",
"mightyena":"True",
"linoone":"True",
"wurmple":"True",
"lotad":"True",
"lombre":"True",
"ludicolo":"True",
"seedot":"True",
"nuzleaf":"True",
"shiftry":"True",
"ralts":"True",
"kirlia":"True",
"gardevoir":"True",
"shroomish":"True",
"breloom":"True",
"slakoth":"True",
"vigoroth":"True",
"slaking":"True",
"whismur":"True",
"loudred":"True",
"exploud":"True",
"makuhita":"True",
"hariyama":"True",
"nosepass":"True",
"delcatty":"True",
"sableye":"True",
"mawile":"True",
"aron":"True",
"lairon":"True",
"aggron":"True",
"meditite":"True",
"medicham":"True",
"electrike":"True",
"manectric":"True",
"plusle":"True",
"carvanha":"True",
"sharpedo":"True",
"wailmer":"True",
"wailord":"True",
"numel":"True",
"camerupt":"True",
"torkoal":"True",
"spoink":"True",
"grumpig":"True",
"spinda":"True",
"trapinch":"True",
"vibrava":"True",
"flygon":"True",
"cacnea":"True",
"cacturne":"True",
"zangoose":"True",
"seviper":"True",
"lunatone":"True",
"solrock":"True",
"barboach":"True",
"whiscash":"True",
"corphish":"True",
"crawdaunt":"True",
"baltoy":"True",
"claydol":"True",
"lileep":"True",
"cradily":"True",
"anorith":"True",
"armaldo":"True",
"feebas":"True",
"milotic":"True",
"castform":"True",
"kecleon":"True",
"shuppet":"True",
"banette":"True",
"duskull":"True",
"dusclops":"True",
"tropius":"True",
"chimecho":"True",
"absol":"True",
"snorunt":"True",
"glalie":"True",
"sealeo":"True",
"walrein":"True",
"relicanth":"True",
"luvdisc":"True",
"bagon":"True",
"shelgon":"True",
"salamence":"True",
"beldum":"True",
"metang":"True",
"metagross":"True",
"regirock":"True",
"regice":"True",
"registeel":"True",
"latias":"True",
"latios":"True",
"kyogre":"True",
"groudon":"True",
"rayquaza":"True",
"jirachi":"True",
"deoxys":"True"
	},
    "eggs":{
        "enabled":"False",
        "min_level": "1",
        "max_level": "5"
    },
    "raids":{
        "enabled":"False",
        "default": {
            "min_dist":"0", "max_dist":"inf", "min_cp": "0", "max_cp": "999999", "min_iv":"0", "max_iv":"100",
            "min_atk": "0", "max_atk":"15", "min_def": "0", "max_def":"15", "min_sta": "0", "max_sta":"15",
            "quick_move": null, "charge_move": null, "moveset": null,
            "size": null, "gender": null, "form": null, "ignore_missing": "False"
        },
       "Articuno":"True",
       "Zapdos":"True",
       "Moltres":"True",
       "Mewtwo":"True",
       "Mew":"True",
       "Raikou":"True",
       "Entei":"True",
       "Suicune":"True",
       "Lugia":"True",
       "Ho-Oh":"True",
       "Celebi":"True"
    }
}
